LICENSE
MANIFEST.in
README.rst
requirements.txt
setup.py
pytod/__init__.py
pytod/version.py
pytod.egg-info/PKG-INFO
pytod.egg-info/SOURCES.txt
pytod.egg-info/dependency_links.txt
pytod.egg-info/requires.txt
pytod.egg-info/top_level.txt
pytod/models/__init__.py
pytod/models/abod.py
pytod/models/base.py
pytod/models/basic_operators.py
pytod/models/hbos.py
pytod/models/intermediate_layers.py
pytod/models/knn.py
pytod/models/lof.py
pytod/models/pca.py
pytod/models/quantization.py
pytod/models/sklearn_base.py
pytod/utils/__init__.py
pytod/utils/data.py
pytod/utils/utility.py