Metadata-Version: 2.1
Name: pytod
Version: 0.0.3
Summary: Tensor-based outlier detection. A general GPU-accelerated framework.
Home-page: https://github.com/yzhao062/pytod
Author: Yue Zhao
Author-email: zhaoy@cmu.edu
License: UNKNOWN
Download-URL: https://github.com/yzhao062/pytod/archive/master.zip
Keywords: pytorch,tensor operation,outlier detection,acceleration,data mining,machine learning,python
Platform: UNKNOWN
Classifier: Development Status :: 2 - Pre-Alpha
Classifier: Intended Audience :: Education
Classifier: Intended Audience :: Financial and Insurance Industry
Classifier: Intended Audience :: Science/Research
Classifier: Intended Audience :: Developers
Classifier: Intended Audience :: Information Technology
Classifier: License :: OSI Approved :: BSD License
Classifier: Programming Language :: Python :: 3.5
Classifier: Programming Language :: Python :: 3.6
Classifier: Programming Language :: Python :: 3.7
License-File: LICENSE
